README.md
setup.py
fpbench/__init__.py
fpbench.egg-info/PKG-INFO
fpbench.egg-info/SOURCES.txt
fpbench.egg-info/dependency_links.txt
fpbench.egg-info/top_level.txt