Metadata-Version: 2.1
Name: fpbench
Version: 0.0.1
Summary: FPBench utilities in Python
Home-page: https://github.com/billzorn/fpy
Author: Bill Zorn
Author-email: bill.zorn@gmail.com
License: UNKNOWN
Platform: UNKNOWN
Classifier: Development Status :: 2 - Pre-Alpha
Classifier: Programming Language :: Python :: 3
Classifier: License :: OSI Approved :: MIT License
Classifier: Operating System :: OS Independent
Requires-Python: >=3.6
